provrandom/__init__.py
provrandom/provrandom.py
provrandom-0.0.1.dist-info/METADATA
provrandom-0.0.1.dist-info/WHEEL
provrandom-0.0.1.dist-info/top_level.txt
provrandom-0.0.1.dist-info/RECORD
